docling_serve_sdk/__init__.py
docling_serve_sdk/client.py
docling_serve_sdk/examples.py
docling_serve_sdk/models.py
docling_serve_sdk-1.3.0.dist-info/METADATA
docling_serve_sdk-1.3.0.dist-info/WHEEL
docling_serve_sdk-1.3.0.dist-info/top_level.txt
docling_serve_sdk-1.3.0.dist-info/RECORD
